oai2ollama/__init__.py
oai2ollama/__main__.py
oai2ollama/_app.py
oai2ollama/config.py
oai2ollama-1.2.8.1.dist-info/WHEEL
oai2ollama-1.2.8.1.dist-info/entry_points.txt
oai2ollama-1.2.8.1.dist-info/METADATA
oai2ollama-1.2.8.1.dist-info/RECORD
