Metadata-Version: 2.3
Name: oai2ollama
Version: 1.2.8.1
Summary: Wrap any OpenAI-compatible API into an Ollama-compatible API.
Author: Muspi Merol
Author-email: Muspi Merol <me@promplate.dev>
Requires-Dist: dotenv-pth~=1.0.0
Requires-Dist: fastapi>=0.115.14,<0.129.0
Requires-Dist: httpx[http2]~=0.28.1
Requires-Dist: pydantic-settings>=2.10.1,<2.13.0
Requires-Dist: uvicorn-hmr~=0.1.1
Requires-Python: >=3.12
Project-URL: documentation, https://oai2ollama.vercel.app/
Project-URL: repository, https://github.com/CNSeniorious000/oai2ollama
